pgf.cpython-37m-darwin.so
pgf.dylibs/libpgf.4.dylib
pgf-2.4.dist-info/RECORD
pgf-2.4.dist-info/WHEEL
pgf-2.4.dist-info/top_level.txt
pgf-2.4.dist-info/METADATA
