Metadata-Version: 2.1
Name: pgf
Version: 2.4
Summary: Python bindings to the Grammatical Framework's PGF runtime
Home-page: https://www.grammaticalframework.org/
Author: Krasimir Angelov
Author-email: kr.angelov@gmail.com
License: BSD
Platform: UNKNOWN
